<?xml version="1.0" encoding="UTF-8" ?>
<pbj-schema xmlns="http://gdbots.io/pbj/xsd"
    xmlns:xsi="http://www.w3.org/2001/XMLSchema-instance"
    xsi:schemaLocation="http://gdbots.io/pbj/xsd http://gdbots.io/pbj/xsd/schema.xsd">

  <schema id="pbj:triniti:sys:mixin:search-redirects-request:1-0-0" mixin="true"
      extends="gdbots:ncr:mixin:search-nodes-request:v1" deprecated="true">
    <fields>
      <field name="is_permanent" type="trinary"/>
      <field name="is_vanity" type="trinary"/>
      <field name="sort" type="string-enum">
        <default>title-asc</default>
        <enum id="triniti:sys:search-redirects-sort"/>
      </field>
    </fields>
  </schema>
</pbj-schema>
